pbs_monitoring_tools/__init__.py
pbs_monitoring_tools/__main__.py
pbs_monitoring_tools/pbs_monitoring_tools.py
pbs_monitoring_tools/helpers/helpers.py
pbs_monitoring_tools-0.3.1.dist-info/licenses/LICENSE
pbs_monitoring_tools-0.3.1.dist-info/METADATA
pbs_monitoring_tools-0.3.1.dist-info/WHEEL
pbs_monitoring_tools-0.3.1.dist-info/top_level.txt
pbs_monitoring_tools-0.3.1.dist-info/RECORD
