Metadata-Version: 2.4
Name: pbs_monitoring_tools
Version: 0.3.1
Summary: This project provides tools that use Proxmox Backup Server (PBS) API with Proxmoxer package.
Author-email: Sigilence Technologies <contact@sigilence.com>
License-Expression: BSD-2-Clause
Project-URL: Our Website, https://www.sigilence-technologies.com/
Classifier: Programming Language :: Python :: 3.11
Classifier: Intended Audience :: Developers
Requires-Python: >=3.11
License-File: LICENSE
Requires-Dist: proxmoxer>=2.2.0
Requires-Dist: requests>=2.32.3
Requires-Dist: PyYAML>=6.0.2
Dynamic: license-file
